cachelocal/__init__.py
cachelocal/base.py
cachelocal/dll.py
cachelocal/fifo.py
cachelocal/lru.py
cachelocal/stats.py
cachelocal-0.2.0.dist-info/licenses/LICENSE
cachelocal-0.2.0.dist-info/METADATA
cachelocal-0.2.0.dist-info/WHEEL
cachelocal-0.2.0.dist-info/top_level.txt
cachelocal-0.2.0.dist-info/RECORD
