Metadata-Version: 2.4
Name: cachelocal
Version: 0.2.0
Summary: Thread-safe in-process cache for Python with eviction policies and TTL
Author: Caleb Getahun
License: MIT
Project-URL: Homepage, https://github.com/calebgetahun/cachelocal
Project-URL: Repository, https://github.com/calebgetahun/cachelocal
Project-URL: Issues, https://github.com/calebgetahun/cachelocal/issues
Keywords: cache,lru,fifo,ttl,in-process,eviction
Classifier: Development Status :: 4 - Beta
Classifier: Intended Audience :: Developers
Classifier: License :: OSI Approved :: MIT License
Classifier: Programming Language :: Python :: 3
Classifier: Programming Language :: Python :: 3.9
Classifier: Programming Language :: Python :: 3.10
Classifier: Programming Language :: Python :: 3.11
Classifier: Programming Language :: Python :: 3.12
Requires-Python: >=3.9
License-File: LICENSE
Provides-Extra: dev
Requires-Dist: pytest; extra == "dev"
Requires-Dist: pytest-cov; extra == "dev"
Dynamic: license-file
